wait_for_cassandra/__init__.py
wait_for_cassandra/base.py
wait_for_cassandra/run.py
wait_for_cassandra-1.8.dist-info/LICENSE
wait_for_cassandra-1.8.dist-info/METADATA
wait_for_cassandra-1.8.dist-info/WHEEL
wait_for_cassandra-1.8.dist-info/entry_points.txt
wait_for_cassandra-1.8.dist-info/top_level.txt
wait_for_cassandra-1.8.dist-info/RECORD
